{
  "parent": "lap:adventure/summon_snow_golem",
  "display": {
    "icon": {
      "item": "minecraft:player_head",
      "nbt": "{SkullOwner:{Id:\"7e98f005-fd35-433b-983e-5dc2d3bab0f4\",Properties:{textures:[{Value:\"eyJ0ZXh0dXJlcyI6eyJTS0lOIjp7InVybCI6Imh0dHA6Ly90ZXh0dXJlcy5taW5lY3JhZnQubmV0L3RleHR1cmUvMWZkZmQxZjc1MzhjMDQwMjU4YmU3YTkxNDQ2ZGE4OWVkODQ1Y2M1ZWY3MjhlYjVlNjkwNTQzMzc4ZmNmNCJ9fX0=\"}]}}}"
    },
    "title": {
      "translate": "Face Reveal"
    },
    "description": {
      "translate": "Shear the pumpkin off a  snow golem"
    },
    "frame": "task",
    "show_toast": true,
    "announce_to_chat": true,
    "hidden": false
  },
  "criteria": {
    "never": {
      "trigger": "impossible"
    }
  },
  "requirements": [
    [
      "never"
    ]
  ]
}