{
  "parent": "lap:enchanting/root",
  "display": {
    "icon": {
      "item": "minecraft:anvil"
    },
    "title": {
      "translate": "Smithy"
    },
    "description": {
      "translate": "Craft an Anvil"
    },
    "frame": "task",
    "show_toast": true,
    "announce_to_chat": true,
    "hidden": false
  },
  "criteria": {
    "anvil": {
      "trigger": "minecraft:inventory_changed",
      "conditions": {
        "items": [
          {
            "item": "minecraft:anvil"
          }
        ]
      }
    }
  },
  "requirements": [
    [
      "anvil"
    ]
  ]
}